{
  "info": {
    "name": "example electron FCM",
    "_postman_id": "996a2513-7fd5-e493-50f3-932ef9fb7473",
    "description": "",
    "schema": "https://schema.getpostman.com/json/collection/v2.1.0/collection.json"
  },
  "item": [
    {
      "name": "FCM firebase cloud message to specific device example",
      "request": {
        "method": "POST",
        "header": [
          {
            "key": "Authorization",
            "value": "key=AAAA5lTZcRw:APA91bGnzX27rZ4mf8ZFDGm8Zf0Dqt0jDu3-dZ4SvlbIOLidF9k43X0MztMChJjQX1d1zCizkexTF0criDACzQfPWOOD8DlwZ8nWTX8pAhmdml0Z148l_LKitBbpA9tS3NVHwu70y_Jj"
          },
          {
            "key": "Content-Type",
            "value": "application/json"
          }
        ],
        "body": {
          "mode": "raw",
          "raw": "{\n  \"to\" : \"fSpBEvZKFs4:APA91bEF9x6zApI6VvjfQLwkMl81t3meE3otuW-ejrEYvHwPDMOvi6-iTt_iUG2Uv5rZ42I2DP87myxSNJjahrkYSmSt2HVEYKUUb3I4bKha1ZCXRrP4EIzr8uA8YbTW3MxxIINaS5Mh\",\n  \"notification\" : {\n    \"title\" : \"example title\",\n    \"body\" : \"example body\"\n  },\n  \"data\" : {\n\t\"foo\" : \"bar\",\n    \"refresh_data\" : 1\n  }\n}"
        },
        "url": {
          "raw": "https://fcm.googleapis.com/fcm/send",
          "protocol": "https",
          "host": ["fcm", "googleapis", "com"],
          "path": ["fcm", "send"]
        },
        "description": ""
      },
      "response": []
    }
  ]
}
